txt2tags.py
txt2tags-3.7.dist-info/COPYING
txt2tags-3.7.dist-info/METADATA
txt2tags-3.7.dist-info/WHEEL
txt2tags-3.7.dist-info/entry_points.txt
txt2tags-3.7.dist-info/top_level.txt
txt2tags-3.7.dist-info/RECORD
